cacheback/__init__.py
cacheback/apps.py
cacheback/base.py
cacheback/decorators.py
cacheback/jobs.py
cacheback/models.py
cacheback/rq_tasks.py
cacheback/tasks.py
cacheback/utils.py
django_cacheback-4.0.0.dist-info/METADATA
django_cacheback-4.0.0.dist-info/WHEEL
django_cacheback-4.0.0.dist-info/licenses/LICENSE
django_cacheback-4.0.0.dist-info/RECORD
