Metadata-Version: 2.4
Name: django-cacheback
Version: 4.0.0
Summary: Caching library for Django that uses Celery or RQ to refresh cache items asynchronously
License: MIT
License-File: LICENSE
Keywords: flake8,markdown,lint
Author: David Winterbottom
Author-email: david.winterbottom@gmail.com
Requires-Python: >=3.10.0,<4
Classifier: Development Status :: 5 - Production/Stable
Classifier: Environment :: Web Environment
Classifier: Framework :: Django
Classifier: Intended Audience :: Developers
Classifier: License :: OSI Approved :: MIT License
Classifier: Operating System :: Unix
Classifier: Programming Language :: Python
Classifier: Programming Language :: Python :: 3
Classifier: Programming Language :: Python :: 3.10
Classifier: Programming Language :: Python :: 3.11
Classifier: Programming Language :: Python :: 3.12
Classifier: Programming Language :: Python :: 3.13
Classifier: Programming Language :: Python :: 3.14
Provides-Extra: celery
Provides-Extra: docs
Provides-Extra: rq
Requires-Dist: Sphinx (>=3.3.0,<4) ; extra == "docs"
Requires-Dist: celery (>=5.0) ; extra == "celery"
Requires-Dist: django (>=5.2)
Requires-Dist: django-rq (>=3) ; extra == "rq"
Project-URL: Homepage, https://github.com/codeinthehole/django-cacheback
Project-URL: Repository, https://github.com/codeinthehole/django-cacheback
